{"yes":1063054,"no":1072621,"total":2135675,"yes_pct":49.78,"no_pct":50.22,"precincts_part":2534,"precincts_rep":2083,"pct_reporting":82.2,"created_at":"2026-04-22T00:23:21.5571085Z","reg_active":6077919,"reg_all":6386900,"ab_issued":1496794,"ab_voted":1369523,"turnout_pct":35.14,"ab_banked_pct":22.5,"ab_out_counted":838331,"ab_outstanding":531192,"margin_vs_outstanding":-521625,"ab_dem_outstanding":312390,"ab_rep_outstanding":215391,"ab_unk_outstanding":5912,"n_not_reported":28,"n_in_person_only":6,"n_mailed_only":8,"n_all_reported":89,"n_final":2}